{"node": {"id": "Q4151224", "type": "Person", "name": {"zh-cn": ["关向应"], "en": []}, "properties": {"lifetime": "1902-09-10 - 1946-07-21"}}, "relationships": [{"source": "Q715411", "target": "Q4151224", "type": "MET_WITH", "properties": {"start_date": "1935-11"}}, {"source": "Q1369370", "target": "Q4151224", "type": "FRIEND_OF", "properties": {"start_date": "1931-06"}}, {"source": "Q4151224", "target": "Q513976", "type": "PUSHED"}, {"source": "Q4151224", "target": "Q190338", "type": "MEMBER_OF", "properties": {"start_date": "1930-03", "end_date": "1930-08"}}]}