{
  "nodes": [
    {
      "id": "清仁宗",
      "type": "Person",
      "name": {
        "zh-cn": [
          "清仁宗",
          "嘉庆帝",
          "颙琰",
          "永琰",
          "嘉庆皇帝"
        ],
        "en": []
      },
      "properties": {
        "period": "1796-02-09 - 1820-09-02",
        "lifetime": "1760-11-13 - 1820-09-02",
        "gender": "Male",
        "location": {
          "zh-cn": "顺天府",
          "en": ""
        },
        "birth_place": {
          "zh-cn": "圆明园",
          "en": ""
        },
        "death_place": {
          "zh-cn": "避暑山庄",
          "en": ""
        },
        "description": {
          "zh-cn": "中国清朝第七位皇帝，清军入关后的第五位皇帝。",
          "en": ""
        }
      }
    },
    {
      "id": "乾隆帝",
      "type": "Person",
      "name": {
        "zh-cn": [
          "乾隆帝",
          "弘历",
          "清高宗"
        ],
        "en": []
      },
      "properties": {
        "gender": "Male",
        "description": {
          "zh-cn": "清朝第六位皇帝，清仁宗之父。",
          "en": ""
        }
      }
    },
    {
      "id": "孝仪纯皇后",
      "type": "Person",
      "name": {
        "zh-cn": [
          "孝仪纯皇后",
          "魏佳氏"
        ],
        "en": []
      },
      "properties": {
        "gender": "Female",
        "description": {
          "zh-cn": "乾隆帝的皇贵妃，嘉庆帝的生母。",
          "en": ""
        }
      }
    },
    {
      "id": "道光帝",
      "type": "Person",
      "name": {
        "zh-cn": [
          "道光帝",
          "旻宁",
          "清宣宗"
        ],
        "en": []
      },
      "properties": {
        "gender": "Male",
        "description": {
          "zh-cn": "清朝第八位皇帝，嘉庆帝的次子和继任者。",
          "en": ""
        }
      }
    },
    {
      "id": "孝淑睿皇后",
      "type": "Person",
      "name": {
        "zh-cn": [
          "孝淑睿皇后",
          "喜塔腊氏"
        ],
        "en": []
      },
      "properties": {
        "gender": "Female",
        "description": {
          "zh-cn": "嘉庆帝的原配妻子和第一任皇后。",
          "en": ""
        }
      }
    },
    {
      "id": "孝和睿皇后",
      "type": "Person",
      "name": {
        "zh-cn": [
          "孝和睿皇后",
          "钮祜禄氏"
        ],
        "en": []
      },
      "properties": {
        "gender": "Female",
        "description": {
          "zh-cn": "嘉庆帝的第二任皇后。",
          "en": ""
        }
      }
    },
    {
      "id": "和裕皇贵妃",
      "type": "Person",
      "name": {
        "zh-cn": [
          "和裕皇贵妃",
          "刘佳氏"
        ],
        "en": []
      },
      "properties": {
        "gender": "Female"
      }
    },
    {
      "id": "恭顺皇贵妃",
      "type": "Person",
      "name": {
        "zh-cn": [
          "恭顺皇贵妃",
          "钮祜禄氏"
        ],
        "en": []
      },
      "properties": {
        "gender": "Female"
      }
    },
    {
      "id": "绵恺",
      "type": "Person",
      "name": {
        "zh-cn": [
          "绵恺",
          "惇恪亲王"
        ],
        "en": []
      },
      "properties": {
        "gender": "Male"
      }
    },
    {
      "id": "绵忻",
      "type": "Person",
      "name": {
        "zh-cn": [
          "绵忻",
          "瑞怀亲王"
        ],
        "en": []
      },
      "properties": {
        "gender": "Male"
      }
    },
    {
      "id": "绵愉",
      "type": "Person",
      "name": {
        "zh-cn": [
          "绵愉",
          "惠端亲王"
        ],
        "en": []
      },
      "properties": {
        "gender": "Male"
      }
    },
    {
      "id": "穆郡王",
      "type": "Person",
      "name": {
        "zh-cn": [
          "穆郡王"
        ],
        "en": []
      },
      "properties": {
        "gender": "Male",
        "description": {
          "zh-cn": "嘉庆帝皇长子，早夭。",
          "en": ""
        }
      }
    },
    {
      "id": "庄敬和硕公主",
      "type": "Person",
      "name": {
        "zh-cn": [
          "庄敬和硕公主"
        ],
        "en": []
      },
      "properties": {
        "gender": "Female"
      }
    },
    {
      "id": "庄静固伦公主",
      "type": "Person",
      "name": {
        "zh-cn": [
          "庄静固伦公主"
        ],
        "en": []
      },
      "properties": {
        "gender": "Female"
      }
    },
    {
      "id": "慧安和硕公主",
      "type": "Person",
      "name": {
        "zh-cn": [
          "慧安和硕公主"
        ],
        "en": []
      },
      "properties": {
        "gender": "Female"
      }
    },
    {
      "id": "慧愍固伦公主",
      "type": "Person",
      "name": {
        "zh-cn": [
          "慧愍固伦公主"
        ],
        "en": []
      },
      "properties": {
        "gender": "Female"
      }
    },
    {
      "id": "逊嫔",
      "type": "Person",
      "name": {
        "zh-cn": [
          "逊嫔",
          "沈佳氏"
        ],
        "en": []
      },
      "properties": {
        "gender": "Female"
      }
    },
    {
      "id": "和珅",
      "type": "Person",
      "name": {
        "zh-cn": [
          "和珅"
        ],
        "en": []
      },
      "properties": {
        "gender": "Male",
        "description": {
          "zh-cn": "乾隆朝权臣，嘉庆帝亲政后被赐死。",
          "en": ""
        }
      }
    },
    {
      "id": "川楚教乱",
      "type": "Event",
      "name": {
        "zh-cn": [
          "川楚教乱"
        ],
        "en": []
      },
      "properties": {
        "period": "1796-10 - ",
        "description": {
          "zh-cn": "嘉庆年间爆发的大规模白莲教起义。",
          "en": ""
        }
      }
    },
    {
      "id": "白莲教",
      "type": "Movement",
      "name": {
        "zh-cn": [
          "白莲教"
        ],
        "en": []
      },
      "properties": {}
    },
    {
      "id": "王三槐",
      "type": "Person",
      "name": {
        "zh-cn": [
          "王三槐"
        ],
        "en": []
      },
      "properties": {
        "gender": "Male",
        "description": {
          "zh-cn": "川楚教乱首领之一。",
          "en": ""
        }
      }
    },
    {
      "id": "陈德 (清)",
      "type": "Person",
      "name": {
        "zh-cn": [
          "陈德 (清)",
          "陈德"
        ],
        "en": []
      },
      "properties": {
        "gender": "Male",
        "description": {
          "zh-cn": "曾在紫禁城门口行刺嘉庆帝。",
          "en": ""
        }
      }
    },
    {
      "id": "癸酉之变",
      "type": "Event",
      "name": {
        "zh-cn": [
          "癸酉之变"
        ],
        "en": []
      },
      "properties": {
        "period": "1813",
        "description": {
          "zh-cn": "天理教徒攻入紫禁城事件。",
          "en": ""
        }
      }
    },
    {
      "id": "天理教 (中国)",
      "type": "Movement",
      "name": {
        "zh-cn": [
          "天理教 (中国)",
          "天理教"
        ],
        "en": []
      },
      "properties": {}
    },
    {
      "id": "林清",
      "type": "Person",
      "name": {
        "zh-cn": [
          "林清"
        ],
        "en": []
      },
      "properties": {
        "gender": "Male",
        "description": {
          "zh-cn": "天理教首领，癸酉之变的发动者。",
          "en": ""
        }
      }
    },
    {
      "id": "阮福映",
      "type": "Person",
      "name": {
        "zh-cn": [
          "阮福映"
        ],
        "en": []
      },
      "properties": {
        "gender": "Male",
        "description": {
          "zh-cn": "安南国王，国号被嘉庆帝改为“越南”。",
          "en": ""
        }
      }
    },
    {
      "id": "越南",
      "type": "Location",
      "name": {
        "zh-cn": [
          "越南"
        ],
        "en": []
      },
      "properties": {}
    },
    {
      "id": "尤里·亚历山德罗夫·戈洛夫金",
      "type": "Person",
      "name": {
        "zh-cn": [
          "尤里·亚历山德罗夫·戈洛夫金",
          "戈洛夫金"
        ],
        "en": []
      },
      "properties": {
        "gender": "Male",
        "description": {
          "zh-cn": "俄国外交官，因礼仪问题其使团被嘉庆帝驱逐。",
          "en": ""
        }
      }
    },
    {
      "id": "英国",
      "type": "Organization",
      "name": {
        "zh-cn": [
          "英国"
        ],
        "en": []
      },
      "properties": {}
    },
    {
      "id": "吴熊光",
      "type": "Person",
      "name": {
        "zh-cn": [
          "吴熊光"
        ],
        "en": []
      },
      "properties": {
        "gender": "Male",
        "description": {
          "zh-cn": "时任两广总督，因处理英国入侵澳门事件不力被免职。",
          "en": ""
        }
      }
    },
    {
      "id": "天主教",
      "type": "Movement",
      "name": {
        "zh-cn": [
          "天主教"
        ],
        "en": []
      },
      "properties": {}
    },
    {
      "id": "阿美士德使团",
      "type": "Event",
      "name": {
        "zh-cn": [
          "阿美士德使团",
          "阿美士德访华"
        ],
        "en": []
      },
      "properties": {
        "period": "1816"
      }
    },
    {
      "id": "嘉道中衰",
      "type": "Event",
      "name": {
        "zh-cn": [
          "嘉道中衰"
        ],
        "en": []
      },
      "properties": {
        "description": {
          "zh-cn": "指清朝嘉庆、道光年间的社会矛盾激化、国势由盛转衰的时期。",
          "en": ""
        }
      }
    },
    {
      "id": "圆明园",
      "type": "Location",
      "name": {
        "zh-cn": [
          "圆明园"
        ],
        "en": []
      },
      "properties": {}
    },
    {
      "id": "避暑山庄",
      "type": "Location",
      "name": {
        "zh-cn": [
          "避暑山庄"
        ],
        "en": []
      },
      "properties": {}
    }
  ],
  "relationships": [
    {
      "source": "清仁宗",
      "target": "乾隆帝",
      "type": "CHILD_OF",
      "properties": {
        "start_date": "",
        "end_date": "",
        "position": {
          "zh-cn": "",
          "en": ""
        },
        "degree": {
          "zh-cn": "",
          "en": ""
        },
        "description": {
          "zh-cn": "嘉庆帝是乾隆帝第十五子。",
          "en": ""
        }
      }
    },
    {
      "source": "清仁宗",
      "target": "孝仪纯皇后",
      "type": "CHILD_OF",
      "properties": {
        "start_date": "",
        "end_date": "",
        "position": {
          "zh-cn": "",
          "en": ""
        },
        "degree": {
          "zh-cn": "",
          "en": ""
        },
        "description": {
          "zh-cn": "",
          "en": ""
        }
      }
    },
    {
      "source": "清仁宗",
      "target": "圆明园",
      "type": "BORN_IN",
      "properties": {
        "start_date": "1760-11-13",
        "end_date": "1760-11-13",
        "position": {
          "zh-cn": "",
          "en": ""
        },
        "degree": {
          "zh-cn": "",
          "en": ""
        },
        "description": {
          "zh-cn": "",
          "en": ""
        }
      }
    },
    {
      "source": "清仁宗",
      "target": "孝淑睿皇后",
      "type": "SPOUSE_OF",
      "properties": {
        "start_date": "",
        "end_date": "",
        "position": {
          "zh-cn": "",
          "en": ""
        },
        "degree": {
          "zh-cn": "",
          "en": ""
        },
        "description": {
          "zh-cn": "",
          "en": ""
        }
      }
    },
    {
      "source": "清仁宗",
      "target": "孝和睿皇后",
      "type": "SPOUSE_OF",
      "properties": {
        "start_date": "",
        "end_date": "",
        "position": {
          "zh-cn": "",
          "en": ""
        },
        "degree": {
          "zh-cn": "",
          "en": ""
        },
        "description": {
          "zh-cn": "",
          "en": ""
        }
      }
    },
    {
      "source": "道光帝",
      "target": "清仁宗",
      "type": "CHILD_OF",
      "properties": {
        "start_date": "",
        "end_date": "",
        "position": {
          "zh-cn": "",
          "en": ""
        },
        "degree": {
          "zh-cn": "",
          "en": ""
        },
        "description": {
          "zh-cn": "",
          "en": ""
        }
      }
    },
    {
      "source": "道光帝",
      "target": "孝淑睿皇后",
      "type": "CHILD_OF",
      "properties": {
        "start_date": "",
        "end_date": "",
        "position": {
          "zh-cn": "",
          "en": ""
        },
        "degree": {
          "zh-cn": "",
          "en": ""
        },
        "description": {
          "zh-cn": "",
          "en": ""
        }
      }
    },
    {
      "source": "绵恺",
      "target": "清仁宗",
      "type": "CHILD_OF",
      "properties": {
        "start_date": "",
        "end_date": "",
        "position": {
          "zh-cn": "",
          "en": ""
        },
        "degree": {
          "zh-cn": "",
          "en": ""
        },
        "description": {
          "zh-cn": "",
          "en": ""
        }
      }
    },
    {
      "source": "绵恺",
      "target": "孝和睿皇后",
      "type": "CHILD_OF",
      "properties": {
        "start_date": "",
        "end_date": "",
        "position": {
          "zh-cn": "",
          "en": ""
        },
        "degree": {
          "zh-cn": "",
          "en": ""
        },
        "description": {
          "zh-cn": "",
          "en": ""
        }
      }
    },
    {
      "source": "绵忻",
      "target": "清仁宗",
      "type": "CHILD_OF",
      "properties": {
        "start_date": "",
        "end_date": "",
        "position": {
          "zh-cn": "",
          "en": ""
        },
        "degree": {
          "zh-cn": "",
          "en": ""
        },
        "description": {
          "zh-cn": "",
          "en": ""
        }
      }
    },
    {
      "source": "绵忻",
      "target": "孝和睿皇后",
      "type": "CHILD_OF",
      "properties": {
        "start_date": "",
        "end_date": "",
        "position": {
          "zh-cn": "",
          "en": ""
        },
        "degree": {
          "zh-cn": "",
          "en": ""
        },
        "description": {
          "zh-cn": "",
          "en": ""
        }
      }
    },
    {
      "source": "绵愉",
      "target": "清仁宗",
      "type": "CHILD_OF",
      "properties": {
        "start_date": "",
        "end_date": "",
        "position": {
          "zh-cn": "",
          "en": ""
        },
        "degree": {
          "zh-cn": "",
          "en": ""
        },
        "description": {
          "zh-cn": "",
          "en": ""
        }
      }
    },
    {
      "source": "绵愉",
      "target": "恭顺皇贵妃",
      "type": "CHILD_OF",
      "properties": {
        "start_date": "",
        "end_date": "",
        "position": {
          "zh-cn": "",
          "en": ""
        },
        "degree": {
          "zh-cn": "",
          "en": ""
        },
        "description": {
          "zh-cn": "",
          "en": ""
        }
      }
    },
    {
      "source": "穆郡王",
      "target": "和裕皇贵妃",
      "type": "CHILD_OF",
      "properties": {
        "start_date": "",
        "end_date": "",
        "position": {
          "zh-cn": "",
          "en": ""
        },
        "degree": {
          "zh-cn": "",
          "en": ""
        },
        "description": {
          "zh-cn": "",
          "en": ""
        }
      }
    },
    {
      "source": "庄敬和硕公主",
      "target": "和裕皇贵妃",
      "type": "CHILD_OF",
      "properties": {
        "start_date": "",
        "end_date": "",
        "position": {
          "zh-cn": "",
          "en": ""
        },
        "degree": {
          "zh-cn": "",
          "en": ""
        },
        "description": {
          "zh-cn": "",
          "en": ""
        }
      }
    },
    {
      "source": "慧安和硕公主",
      "target": "逊嫔",
      "type": "CHILD_OF",
      "properties": {
        "start_date": "",
        "end_date": "",
        "position": {
          "zh-cn": "",
          "en": ""
        },
        "degree": {
          "zh-cn": "",
          "en": ""
        },
        "description": {
          "zh-cn": "",
          "en": ""
        }
      }
    },
    {
      "source": "慧愍固伦公主",
      "target": "恭顺皇贵妃",
      "type": "CHILD_OF",
      "properties": {
        "start_date": "",
        "end_date": "",
        "position": {
          "zh-cn": "",
          "en": ""
        },
        "degree": {
          "zh-cn": "",
          "en": ""
        },
        "description": {
          "zh-cn": "",
          "en": ""
        }
      }
    },
    {
      "source": "清仁宗",
      "target": "乾隆帝",
      "type": "SUBORDINATE_OF",
      "properties": {
        "start_date": "1796-02-09",
        "end_date": "1799",
        "position": {
          "zh-cn": "皇帝",
          "en": ""
        },
        "degree": {
          "zh-cn": "",
          "en": ""
        },
        "description": {
          "zh-cn": "乾隆帝禅位后仍以太上皇身份训政，掌握实权近三年。",
          "en": ""
        }
      }
    },
    {
      "source": "道光帝",
      "target": "清仁宗",
      "type": "SUBORDINATE_OF",
      "properties": {
        "start_date": "1799",
        "end_date": "1820",
        "position": {
          "zh-cn": "皇太子",
          "en": ""
        },
        "degree": {
          "zh-cn": "",
          "en": ""
        },
        "description": {
          "zh-cn": "",
          "en": ""
        }
      }
    },
    {
      "source": "清仁宗",
      "target": "和珅",
      "type": "ENEMY_OF",
      "properties": {
        "start_date": "1799-02",
        "end_date": "",
        "position": {
          "zh-cn": "",
          "en": ""
        },
        "degree": {
          "zh-cn": "",
          "en": ""
        },
        "description": {
          "zh-cn": "亲政后立即逮捕和珅并将其赐死。",
          "en": ""
        }
      }
    },
    {
      "source": "川楚教乱",
      "target": "清仁宗",
      "type": "BLOCKED",
      "properties": {
        "start_date": "1796-10",
        "end_date": "",
        "position": {
          "zh-cn": "",
          "en": ""
        },
        "degree": {
          "zh-cn": "",
          "en": ""
        },
        "description": {
          "zh-cn": "嘉庆元年爆发的白莲教起义，是嘉庆朝面临的重大内乱。",
          "en": ""
        }
      }
    },
    {
      "source": "白莲教",
      "target": "川楚教乱",
      "type": "PUSHED",
      "properties": {
        "start_date": "",
        "end_date": "",
        "position": {
          "zh-cn": "",
          "en": ""
        },
        "degree": {
          "zh-cn": "",
          "en": ""
        },
        "description": {
          "zh-cn": "川楚教乱是白莲教发动的大规模农民起义。",
          "en": ""
        }
      }
    },
    {
      "source": "王三槐",
      "target": "清仁宗",
      "type": "ENEMY_OF",
      "properties": {
        "start_date": "",
        "end_date": "",
        "position": {
          "zh-cn": "",
          "en": ""
        },
        "degree": {
          "zh-cn": "",
          "en": ""
        },
        "description": {
          "zh-cn": "川楚教乱的白莲教首领之一。",
          "en": ""
        }
      }
    },
    {
      "source": "陈德 (清)",
      "target": "清仁宗",
      "type": "ENEMY_OF",
      "properties": {
        "start_date": "1803",
        "end_date": "",
        "position": {
          "zh-cn": "",
          "en": ""
        },
        "degree": {
          "zh-cn": "",
          "en": ""
        },
        "description": {
          "zh-cn": "在紫禁城门口行刺嘉庆帝。",
          "en": ""
        }
      }
    },
    {
      "source": "癸酉之变",
      "target": "清仁宗",
      "type": "BLOCKED",
      "properties": {
        "start_date": "1813-09",
        "end_date": "",
        "position": {
          "zh-cn": "",
          "en": ""
        },
        "degree": {
          "zh-cn": "",
          "en": ""
        },
        "description": {
          "zh-cn": "天理教徒攻入紫禁城，是清朝历史上一次严重的宫禁事件。",
          "en": ""
        }
      }
    },
    {
      "source": "天理教 (中国)",
      "target": "癸酉之变",
      "type": "PUSHED",
      "properties": {
        "start_date": "",
        "end_date": "",
        "position": {
          "zh-cn": "",
          "en": ""
        },
        "degree": {
          "zh-cn": "",
          "en": ""
        },
        "description": {
          "zh-cn": "",
          "en": ""
        }
      }
    },
    {
      "source": "林清",
      "target": "癸酉之变",
      "type": "PUSHED",
      "properties": {
        "start_date": "",
        "end_date": "",
        "position": {
          "zh-cn": "",
          "en": ""
        },
        "degree": {
          "zh-cn": "",
          "en": ""
        },
        "description": {
          "zh-cn": "率领天理教徒攻入紫禁城。",
          "en": ""
        }
      }
    },
    {
      "source": "清仁宗",
      "target": "越南",
      "type": "INFLUENCED",
      "properties": {
        "start_date": "1802",
        "end_date": "",
        "position": {
          "zh-cn": "",
          "en": ""
        },
        "degree": {
          "zh-cn": "",
          "en": ""
        },
        "description": {
          "zh-cn": "应安南国王阮福映请求，将其国号从“南越”改为“越南”。",
          "en": ""
        }
      }
    },
    {
      "source": "清仁宗",
      "target": "尤里·亚历山德罗夫·戈洛夫金",
      "type": "BLOCKED",
      "properties": {
        "start_date": "1806-01",
        "end_date": "",
        "position": {
          "zh-cn": "",
          "en": ""
        },
        "degree": {
          "zh-cn": "",
          "en": ""
        },
        "description": {
          "zh-cn": "因俄国使臣戈洛夫金拒绝行三跪九叩礼，降旨将其使团护送回国。",
          "en": ""
        }
      }
    },
    {
      "source": "清仁宗",
      "target": "英国",
      "type": "BLOCKED",
      "properties": {
        "start_date": "1808-07",
        "end_date": "1808-10",
        "position": {
          "zh-cn": "",
          "en": ""
        },
        "degree": {
          "zh-cn": "",
          "en": ""
        },
        "description": {
          "zh-cn": "针对英国派兵入侵澳门，下令封锁水路并最终迫使其撤离。",
          "en": ""
        }
      }
    },
    {
      "source": "清仁宗",
      "target": "天主教",
      "type": "BLOCKED",
      "properties": {
        "start_date": "1811-07",
        "end_date": "",
        "position": {
          "zh-cn": "",
          "en": ""
        },
        "degree": {
          "zh-cn": "",
          "en": ""
        },
        "description": {
          "zh-cn": "禁止西洋人在内地居住，禁止人民接触天主教。",
          "en": ""
        }
      }
    },
    {
      "source": "清仁宗",
      "target": "阿美士德使团",
      "type": "BLOCKED",
      "properties": {
        "start_date": "1816",
        "end_date": "",
        "position": {
          "zh-cn": "",
          "en": ""
        },
        "degree": {
          "zh-cn": "",
          "en": ""
        },
        "description": {
          "zh-cn": "因礼仪问题取消觐见，驱逐使团，并拒绝英国提出的外交及通商要求。",
          "en": ""
        }
      }
    },
    {
      "source": "清仁宗",
      "target": "嘉道中衰",
      "type": "PUSHED",
      "properties": {
        "start_date": "",
        "end_date": "",
        "position": {
          "zh-cn": "",
          "en": ""
        },
        "degree": {
          "zh-cn": "",
          "en": ""
        },
        "description": {
          "zh-cn": "其统治时期未能解决社会矛盾，使清朝由盛转衰，进入“嘉道中衰”。",
          "en": ""
        }
      }
    }
  ]
}