{
  "nodes": [
    {
      "id": "中国人民解放军北京卫戍区",
      "type": "Organization",
      "name": {
        "zh-cn": [
          "中国人民解放军北京卫戍区",
          "御林军"
        ],
        "en": [
          "People's Liberation Army Beijing Garrison"
        ]
      },
      "properties": {
        "period": "1949 - ",
        "location": {
          "zh-cn": "北京市",
          "en": "Beijing"
        },
        "description": {
          "zh-cn": "中华人民共和国首都卫戍区的中国人民解放军省级军区，为正军级单位。2016年起隶属中国人民解放军陆军总部，并接受中央军事委员会直接指挥。主要负责和平时期保卫首都安全，战时掩护中央机关转移撤离、防御外敌、反恐及镇暴等任务。",
          "en": "A provincial-level military region of the People's Liberation Army (PLA) responsible for the defense of the capital of the People's Republic of China. It is a corps-level unit. Since 2016, it has been subordinate to the PLA Ground Force Headquarters and receives direct command from the Central Military Commission. Its main responsibilities include safeguarding the capital's security during peacetime, and during wartime, covering the transfer or evacuation of central government organs, defending against foreign enemies, counter-terrorism, and riot control."
        }
      }
    },
    {
      "id": "中国人民解放军陆军",
      "type": "Organization",
      "name": {
        "zh-cn": [
          "中国人民解放军陆军"
        ],
        "en": [
          "People's Liberation Army Ground Force"
        ]
      },
      "properties": {
        "description": {
          "zh-cn": "中国人民解放军的主要组成军种，是陆上作战的主力。",
          "en": "The main service branch of the People's Liberation Army, responsible for land-based military operations."
        }
      }
    },
    {
      "id": "中国人民解放军北京军区",
      "type": "Organization",
      "name": {
        "zh-cn": [
          "中国人民解放军北京军区",
          "北京军区"
        ],
        "en": [
          "Beijing Military Region"
        ]
      },
      "properties": {
        "description": {
          "zh-cn": "中国人民解放军已撤销的七个大军区之一，主要负责首都北京的防务。",
          "en": "One of the seven former military regions of the People's Liberation Army, primarily responsible for the defense of the capital, Beijing."
        }
      }
    },
    {
      "id": "中央军事委员会",
      "type": "Organization",
      "name": {
        "zh-cn": [
          "中央军事委员会"
        ],
        "en": [
          "Central Military Commission"
        ]
      },
      "properties": {
        "description": {
          "zh-cn": "中华人民共和国的最高国家军事机关，统一领导全国武装力量。",
          "en": "The highest national military organ of the People's Republic of China, which commands the nation's armed forces."
        }
      }
    },
    {
      "id": "中华人民共和国",
      "type": "Organization",
      "name": {
        "zh-cn": [
          "中华人民共和国"
        ],
        "en": [
          "People's Republic of China"
        ]
      },
      "properties": {
        "description": {
          "zh-cn": "位于东亚的国家，是世界上人口最多的国家。",
          "en": "A country in East Asia, it is the world's most populous country."
        }
      }
    },
    {
      "id": "北京市",
      "type": "Location",
      "name": {
        "zh-cn": [
          "北京市"
        ],
        "en": [
          "Beijing"
        ]
      },
      "properties": {
        "description": {
          "zh-cn": "中华人民共和国的首都和直辖市。",
          "en": "The capital and a direct-administered municipality of the People's Republic of China."
        }
      }
    },
    {
      "id": "付文化",
      "type": "Person",
      "name": {
        "zh-cn": [
          "付文化"
        ],
        "en": []
      },
      "properties": {
        "gender": "Male",
        "description": {
          "zh-cn": "中国人民解放军陆军少将，现任北京卫戍区司令员。",
          "en": "A major general in the PLA Ground Force, currently serving as the Commander of the Beijing Garrison."
        }
      }
    },
    {
      "id": "朱军 (1971年)",
      "type": "Person",
      "name": {
        "zh-cn": [
          "朱军 (1971年)",
          "朱军"
        ],
        "en": []
      },
      "properties": {
        "gender": "Male",
        "description": {
          "zh-cn": "中国人民解放军陆军少将，现任北京卫戍区政治委员。",
          "en": "A major general in the PLA Ground Force, currently serving as the Political Commissar of the Beijing Garrison."
        }
      }
    },
    {
      "id": "华北军区",
      "type": "Organization",
      "name": {
        "zh-cn": [
          "华北军区"
        ],
        "en": []
      },
      "properties": {
        "description": {
          "zh-cn": "中国人民解放军在解放战争时期设立的一级军区。",
          "en": "A first-level military region established by the People's Liberation Army during the Chinese Civil War."
        }
      }
    },
    {
      "id": "平津卫戍司令部",
      "type": "Organization",
      "name": {
        "zh-cn": [
          "平津卫戍司令部"
        ],
        "en": []
      },
      "properties": {
        "period": "1949-06-29 - ",
        "description": {
          "zh-cn": "中华人民共和国成立初期负责保卫北京和天津的军事机构，是北京卫戍区的前身之一。",
          "en": "A military organization responsible for the defense of Beijing and Tianjin in the early days of the People's Republic of China, and one of the predecessors of the Beijing Garrison."
        }
      }
    },
    {
      "id": "京津卫戍司令部",
      "type": "Organization",
      "name": {
        "zh-cn": [
          "京津卫戍司令部"
        ],
        "en": []
      },
      "properties": {
        "description": {
          "zh-cn": "由平津卫戍司令部改称而来，是北京卫戍区的前身之一。",
          "en": "Renamed from the Peiping-Tientsin Garrison Command, it was one of the predecessors of the Beijing Garrison."
        }
      }
    },
    {
      "id": "聂荣臻",
      "type": "Person",
      "name": {
        "zh-cn": [
          "聂荣臻"
        ],
        "en": []
      },
      "properties": {
        "lifetime": "1899-12-29 - 1992-05-14",
        "gender": "Male",
        "description": {
          "zh-cn": "中国人民解放军元帅，曾任平津卫戍司令部司令员。",
          "en": "A Marshal of the People's Liberation Army, who served as the Commander of the Peiping-Tientsin Garrison Command."
        }
      }
    },
    {
      "id": "杨成武",
      "type": "Person",
      "name": {
        "zh-cn": [
          "杨成武"
        ],
        "en": []
      },
      "properties": {
        "lifetime": "1914-10-27 - 2004-02-14",
        "gender": "Male",
        "description": {
          "zh-cn": "中国人民解放军开国上将，曾任北京军区兼京津卫戍区司令员。",
          "en": "A founding general of the People's Liberation Army, who served as the Commander of the Beijing Military Region and Beijing-Tientsin Garrison."
        }
      }
    },
    {
      "id": "建国门事件",
      "type": "Event",
      "name": {
        "zh-cn": [
          "建国门事件"
        ],
        "en": [
          "1994 Tiananmen shooting"
        ]
      },
      "properties": {
        "period": "1994-09",
        "location": {
          "zh-cn": "北京市",
          "en": "Beijing"
        },
        "description": {
          "zh-cn": "1994年9月，北京卫戍区一名军官田明建在北京市区发动的枪战事件。",
          "en": "A shooting incident initiated by Tian Mingjian, an officer of the Beijing Garrison, in downtown Beijing in September 1994."
        }
      }
    },
    {
      "id": "中国人民解放军警卫第三师",
      "type": "Organization",
      "name": {
        "zh-cn": [
          "中国人民解放军警卫第三师",
          "警卫第三师"
        ],
        "en": [
          "3rd Guard Division of the People's Liberation Army"
        ]
      },
      "properties": {
        "location": {
          "zh-cn": "北京市通州区",
          "en": "Tongzhou District, Beijing"
        },
        "description": {
          "zh-cn": "中国人民解放军北京卫戍区下辖部队。",
          "en": "A subordinate unit of the PLA Beijing Garrison."
        }
      }
    },
    {
      "id": "警卫第十二团",
      "type": "Organization",
      "name": {
        "zh-cn": [
          "警卫第十二团"
        ],
        "en": []
      },
      "properties": {
        "period": " - 1996",
        "description": {
          "zh-cn": "原隶属于中国人民解放军警卫第三师，因建国门事件于1996年被裁撤。",
          "en": "Formerly subordinate to the PLA 3rd Guard Division, it was disbanded in 1996 due to the 1994 Tiananmen shooting."
        }
      }
    },
    {
      "id": "田明建",
      "type": "Person",
      "name": {
        "zh-cn": [
          "田明建"
        ],
        "en": []
      },
      "properties": {
        "gender": "Male",
        "description": {
          "zh-cn": "原北京卫戍区警卫第三师十二团中尉副连长，建国门事件的制造者。",
          "en": "A former First Lieutenant and deputy company commander of the 12th Regiment, 3rd Guard Division of the Beijing Garrison, and the perpetrator of the 1994 Tiananmen shooting."
        }
      }
    },
    {
      "id": "吴烈",
      "type": "Person",
      "name": {
        "zh-cn": [
          "吴烈"
        ],
        "en": []
      },
      "properties": {
        "gender": "Male"
      }
    },
    {
      "id": "曾美",
      "type": "Person",
      "name": {
        "zh-cn": [
          "曾美"
        ],
        "en": []
      },
      "properties": {
        "gender": "Male"
      }
    },
    {
      "id": "李家益",
      "type": "Person",
      "name": {
        "zh-cn": [
          "李家益"
        ],
        "en": []
      },
      "properties": {
        "gender": "Male"
      }
    },
    {
      "id": "傅崇碧",
      "type": "Person",
      "name": {
        "zh-cn": [
          "傅崇碧"
        ],
        "en": []
      },
      "properties": {
        "gender": "Male"
      }
    },
    {
      "id": "温玉成",
      "type": "Person",
      "name": {
        "zh-cn": [
          "温玉成"
        ],
        "en": []
      },
      "properties": {
        "gender": "Male"
      }
    },
    {
      "id": "吴忠 (少将)",
      "type": "Person",
      "name": {
        "zh-cn": [
          "吴忠 (少将)",
          "吴忠"
        ],
        "en": []
      },
      "properties": {
        "gender": "Male"
      }
    },
    {
      "id": "潘焱",
      "type": "Person",
      "name": {
        "zh-cn": [
          "潘焱"
        ],
        "en": []
      },
      "properties": {
        "gender": "Male"
      }
    },
    {
      "id": "李钟玄",
      "type": "Person",
      "name": {
        "zh-cn": [
          "李钟玄"
        ],
        "en": []
      },
      "properties": {
        "gender": "Male"
      }
    },
    {
      "id": "阎同茂",
      "type": "Person",
      "name": {
        "zh-cn": [
          "阎同茂"
        ],
        "en": []
      },
      "properties": {
        "gender": "Male"
      }
    },
    {
      "id": "董学林",
      "type": "Person",
      "name": {
        "zh-cn": [
          "董学林"
        ],
        "en": []
      },
      "properties": {
        "gender": "Male"
      }
    },
    {
      "id": "张志坚 (上将)",
      "type": "Person",
      "name": {
        "zh-cn": [
          "张志坚 (上将)",
          "张志坚"
        ],
        "en": []
      },
      "properties": {
        "gender": "Male"
      }
    },
    {
      "id": "何道泉",
      "type": "Person",
      "name": {
        "zh-cn": [
          "何道泉"
        ],
        "en": []
      },
      "properties": {
        "gender": "Male"
      }
    },
    {
      "id": "刘逢君",
      "type": "Person",
      "name": {
        "zh-cn": [
          "刘逢君"
        ],
        "en": []
      },
      "properties": {
        "gender": "Male"
      }
    },
    {
      "id": "邱金凯",
      "type": "Person",
      "name": {
        "zh-cn": [
          "邱金凯"
        ],
        "en": []
      },
      "properties": {
        "gender": "Male"
      }
    },
    {
      "id": "李少军",
      "type": "Person",
      "name": {
        "zh-cn": [
          "李少军"
        ],
        "en": []
      },
      "properties": {
        "gender": "Male"
      }
    },
    {
      "id": "郑传福",
      "type": "Person",
      "name": {
        "zh-cn": [
          "郑传福"
        ],
        "en": []
      },
      "properties": {
        "gender": "Male"
      }
    },
    {
      "id": "潘良时",
      "type": "Person",
      "name": {
        "zh-cn": [
          "潘良时"
        ],
        "en": []
      },
      "properties": {
        "gender": "Male"
      }
    },
    {
      "id": "王春宁",
      "type": "Person",
      "name": {
        "zh-cn": [
          "王春宁"
        ],
        "en": []
      },
      "properties": {
        "gender": "Male"
      }
    },
    {
      "id": "刘仁",
      "type": "Person",
      "name": {
        "zh-cn": [
          "刘仁"
        ],
        "en": []
      },
      "properties": {
        "gender": "Male"
      }
    },
    {
      "id": "刘绍文",
      "type": "Person",
      "name": {
        "zh-cn": [
          "刘绍文"
        ],
        "en": []
      },
      "properties": {
        "gender": "Male"
      }
    },
    {
      "id": "黄作珍",
      "type": "Person",
      "name": {
        "zh-cn": [
          "黄作珍"
        ],
        "en": []
      },
      "properties": {
        "gender": "Male"
      }
    },
    {
      "id": "杨俊生 (1916年)",
      "type": "Person",
      "name": {
        "zh-cn": [
          "杨俊生 (1916年)",
          "杨俊生"
        ],
        "en": []
      },
      "properties": {
        "gender": "Male"
      }
    },
    {
      "id": "刘福 (少将)",
      "type": "Person",
      "name": {
        "zh-cn": [
          "刘福 (少将)",
          "刘福"
        ],
        "en": []
      },
      "properties": {
        "gender": "Male"
      }
    },
    {
      "id": "吴德",
      "type": "Person",
      "name": {
        "zh-cn": [
          "吴德"
        ],
        "en": []
      },
      "properties": {
        "gender": "Male"
      }
    },
    {
      "id": "谢富治",
      "type": "Person",
      "name": {
        "zh-cn": [
          "谢富治"
        ],
        "en": []
      },
      "properties": {
        "gender": "Male"
      }
    },
    {
      "id": "许志奋",
      "type": "Person",
      "name": {
        "zh-cn": [
          "许志奋"
        ],
        "en": []
      },
      "properties": {
        "gender": "Male"
      }
    },
    {
      "id": "李进民",
      "type": "Person",
      "name": {
        "zh-cn": [
          "李进民"
        ],
        "en": []
      },
      "properties": {
        "gender": "Male"
      }
    },
    {
      "id": "林乎加",
      "type": "Person",
      "name": {
        "zh-cn": [
          "林乎加"
        ],
        "en": []
      },
      "properties": {
        "gender": "Male"
      }
    },
    {
      "id": "段君毅",
      "type": "Person",
      "name": {
        "zh-cn": [
          "段君毅"
        ],
        "en": []
      },
      "properties": {
        "gender": "Male"
      }
    },
    {
      "id": "张宝康",
      "type": "Person",
      "name": {
        "zh-cn": [
          "张宝康"
        ],
        "en": []
      },
      "properties": {
        "gender": "Male"
      }
    },
    {
      "id": "杨惠川",
      "type": "Person",
      "name": {
        "zh-cn": [
          "杨惠川"
        ],
        "en": []
      },
      "properties": {
        "gender": "Male"
      }
    },
    {
      "id": "李文华 (中将)",
      "type": "Person",
      "name": {
        "zh-cn": [
          "李文华 (中将)",
          "李文华"
        ],
        "en": []
      },
      "properties": {
        "gender": "Male"
      }
    },
    {
      "id": "孙本胜",
      "type": "Person",
      "name": {
        "zh-cn": [
          "孙本胜"
        ],
        "en": []
      },
      "properties": {
        "gender": "Male"
      }
    },
    {
      "id": "董吉顺",
      "type": "Person",
      "name": {
        "zh-cn": [
          "董吉顺"
        ],
        "en": []
      },
      "properties": {
        "gender": "Male"
      }
    },
    {
      "id": "刘福连",
      "type": "Person",
      "name": {
        "zh-cn": [
          "刘福连"
        ],
        "en": []
      },
      "properties": {
        "gender": "Male"
      }
    },
    {
      "id": "高东璐",
      "type": "Person",
      "name": {
        "zh-cn": [
          "高东璐"
        ],
        "en": []
      },
      "properties": {
        "gender": "Male"
      }
    },
    {
      "id": "姜勇 (中将)",
      "type": "Person",
      "name": {
        "zh-cn": [
          "姜勇 (中将)",
          "姜勇"
        ],
        "en": []
      },
      "properties": {
        "gender": "Male"
      }
    },
    {
      "id": "张凡迪",
      "type": "Person",
      "name": {
        "zh-cn": [
          "张凡迪"
        ],
        "en": []
      },
      "properties": {
        "gender": "Male"
      }
    }
  ],
  "relationships": [
    {
      "source": "中国人民解放军北京卫戍区",
      "target": "中国人民解放军陆军",
      "type": "SUBORDINATE_OF",
      "properties": {
        "start_date": "2016-08",
        "description": {
          "zh-cn": "2016年8月，北京卫戍区由原北京军区转隶陆军总部。",
          "en": "In August 2016, the Beijing Garrison was transferred from the former Beijing Military Region to the Ground Force Headquarters."
        }
      }
    },
    {
      "source": "中国人民解放军北京卫戍区",
      "target": "中国人民解放军北京军区",
      "type": "SUBORDINATE_OF",
      "properties": {
        "end_date": "2016-08",
        "description": {
          "zh-cn": "2016年8月前，北京卫戍区隶属于北京军区。",
          "en": "Before August 2016, the Beijing Garrison was subordinate to the Beijing Military Region."
        }
      }
    },
    {
      "source": "中国人民解放军北京卫戍区",
      "target": "中央军事委员会",
      "type": "SUBORDINATE_OF",
      "properties": {
        "description": {
          "zh-cn": "北京卫戍区接受中央军事委员会直接指挥。",
          "en": "The Beijing Garrison receives direct command from the Central Military Commission."
        }
      }
    },
    {
      "source": "华北军区",
      "target": "平津卫戍司令部",
      "type": "FOUNDED",
      "properties": {
        "start_date": "1949-06-29",
        "description": {
          "zh-cn": "1949年6月29日，华北军区成立平津卫戍司令部。",
          "en": "On June 29, 1949, the North China Military Region established the Peiping-Tientsin Garrison Command."
        }
      }
    },
    {
      "source": "平津卫戍司令部",
      "target": "京津卫戍司令部",
      "type": "INFLUENCED",
      "properties": {
        "description": {
          "zh-cn": "中华人民共和国成立后，平津卫戍司令部改称京津卫戍司令部。",
          "en": "After the founding of the People's Republic of China, the Peiping-Tientsin Garrison Command was renamed the Beijing-Tientsin Garrison Command."
        }
      }
    },
    {
      "source": "聂荣臻",
      "target": "平津卫戍司令部",
      "type": "MEMBER_OF",
      "properties": {
        "start_date": "1949-06",
        "position": {
          "zh-cn": "司令员 (兼)",
          "en": "Commander (concurrently)"
        }
      }
    },
    {
      "source": "杨成武",
      "target": "中国人民解放军北京军区",
      "type": "MEMBER_OF",
      "properties": {
        "start_date": "1955-04",
        "position": {
          "zh-cn": "司令员",
          "en": "Commander"
        },
        "description": {
          "zh-cn": "1955年4月任北京军区兼京津卫戍区司令员。",
          "en": "In April 1955, he was appointed Commander of the Beijing Military Region and concurrently the Beijing-Tientsin Garrison."
        }
      }
    },
    {
      "source": "田明建",
      "target": "建国门事件",
      "type": "PUSHED",
      "properties": {
        "start_date": "1994-09",
        "description": {
          "zh-cn": "田明建在北京市中心引发枪战，造成建国门事件。",
          "en": "Tian Mingjian initiated a shootout in central Beijing, causing the 1994 Tiananmen shooting incident."
        }
      }
    },
    {
      "source": "田明建",
      "target": "警卫第十二团",
      "type": "MEMBER_OF",
      "properties": {
        "position": {
          "zh-cn": "中尉副连长",
          "en": "First Lieutenant Deputy Company Commander"
        }
      }
    },
    {
      "source": "警卫第十二团",
      "target": "中国人民解放军警卫第三师",
      "type": "SUBORDINATE_OF",
      "properties": {}
    },
    {
      "source": "建国门事件",
      "target": "警卫第十二团",
      "type": "BLOCKED",
      "properties": {
        "start_date": "1996",
        "description": {
          "zh-cn": "警卫第十二团因建国门事件于1996年被裁撤。",
          "en": "The 12th Guard Regiment was disbanded in 1996 due to the 1994 Tiananmen shooting incident."
        }
      }
    },
    {
      "source": "付文化",
      "target": "中国人民解放军北京卫戍区",
      "type": "MEMBER_OF",
      "properties": {
        "start_date": "2020-04",
        "position": {
          "zh-cn": "司令员",
          "en": "Commander"
        }
      }
    },
    {
      "source": "王春宁",
      "target": "中国人民解放军北京卫戍区",
      "type": "MEMBER_OF",
      "properties": {
        "start_date": "2016-07",
        "end_date": "2020-04",
        "position": {
          "zh-cn": "司令员",
          "en": "Commander"
        }
      }
    },
    {
      "source": "潘良时",
      "target": "中国人民解放军北京卫戍区",
      "type": "MEMBER_OF",
      "properties": {
        "start_date": "2013-12",
        "end_date": "2016-07",
        "position": {
          "zh-cn": "司令员",
          "en": "Commander"
        }
      }
    },
    {
      "source": "郑传福",
      "target": "中国人民解放军北京卫戍区",
      "type": "MEMBER_OF",
      "properties": {
        "start_date": "2009-12",
        "end_date": "2013-12",
        "position": {
          "zh-cn": "司令员",
          "en": "Commander"
        }
      }
    },
    {
      "source": "李少军",
      "target": "中国人民解放军北京卫戍区",
      "type": "MEMBER_OF",
      "properties": {
        "start_date": "2006-12",
        "end_date": "2009-12",
        "position": {
          "zh-cn": "司令员",
          "en": "Commander"
        }
      }
    },
    {
      "source": "邱金凯",
      "target": "中国人民解放军北京卫戍区",
      "type": "MEMBER_OF",
      "properties": {
        "start_date": "2005-12",
        "end_date": "2006-12",
        "position": {
          "zh-cn": "司令员",
          "en": "Commander"
        }
      }
    },
    {
      "source": "刘逢君",
      "target": "中国人民解放军北京卫戍区",
      "type": "MEMBER_OF",
      "properties": {
        "start_date": "1994-12",
        "end_date": "2005-12",
        "position": {
          "zh-cn": "司令员",
          "en": "Commander"
        }
      }
    },
    {
      "source": "何道泉",
      "target": "中国人民解放军北京卫戍区",
      "type": "MEMBER_OF",
      "properties": {
        "start_date": "1993-12",
        "end_date": "1994-12",
        "position": {
          "zh-cn": "司令员",
          "en": "Commander"
        }
      }
    },
    {
      "source": "张志坚 (上将)",
      "target": "中国人民解放军北京卫戍区",
      "type": "MEMBER_OF",
      "properties": {
        "start_date": "1992-11",
        "end_date": "1993-12",
        "position": {
          "zh-cn": "司令员",
          "en": "Commander"
        }
      }
    },
    {
      "source": "董学林",
      "target": "中国人民解放军北京卫戍区",
      "type": "MEMBER_OF",
      "properties": {
        "start_date": "1990-04",
        "end_date": "1992-11",
        "position": {
          "zh-cn": "司令员",
          "en": "Commander"
        }
      }
    },
    {
      "source": "阎同茂",
      "target": "中国人民解放军北京卫戍区",
      "type": "MEMBER_OF",
      "properties": {
        "start_date": "1985-06",
        "end_date": "1990-04",
        "position": {
          "zh-cn": "司令员",
          "en": "Commander"
        }
      }
    },
    {
      "source": "李钟玄",
      "target": "中国人民解放军北京卫戍区",
      "type": "MEMBER_OF",
      "properties": {
        "start_date": "1983-09",
        "end_date": "1985-06",
        "position": {
          "zh-cn": "司令员",
          "en": "Commander"
        }
      }
    },
    {
      "source": "潘焱",
      "target": "中国人民解放军北京卫戍区",
      "type": "MEMBER_OF",
      "properties": {
        "start_date": "1979-02",
        "end_date": "1983-09",
        "position": {
          "zh-cn": "司令员",
          "en": "Commander"
        }
      }
    },
    {
      "source": "傅崇碧",
      "target": "中国人民解放军北京卫戍区",
      "type": "MEMBER_OF",
      "properties": {
        "start_date": [
          "1966-05",
          "1977-09"
        ],
        "end_date": [
          "1968-03",
          "1979-01"
        ],
        "position": {
          "zh-cn": "司令员",
          "en": "Commander"
        }
      }
    },
    {
      "source": "吴忠 (少将)",
      "target": "中国人民解放军北京卫戍区",
      "type": "MEMBER_OF",
      "properties": {
        "start_date": "1970-05",
        "end_date": "1977-09",
        "position": {
          "zh-cn": "司令员",
          "en": "Commander"
        }
      }
    },
    {
      "source": "温玉成",
      "target": "中国人民解放军北京卫戍区",
      "type": "MEMBER_OF",
      "properties": {
        "start_date": "1968-03",
        "end_date": "1970-05",
        "position": {
          "zh-cn": "司令员",
          "en": "Commander"
        }
      }
    },
    {
      "source": "李家益",
      "target": "中国人民解放军北京卫戍区",
      "type": "MEMBER_OF",
      "properties": {
        "start_date": "1965-07",
        "end_date": "1966-05",
        "position": {
          "zh-cn": "司令员",
          "en": "Commander"
        }
      }
    },
    {
      "source": "曾美",
      "target": "中国人民解放军北京卫戍区",
      "type": "MEMBER_OF",
      "properties": {
        "start_date": "1963-11",
        "end_date": "1965-05",
        "position": {
          "zh-cn": "司令员",
          "en": "Commander"
        }
      }
    },
    {
      "source": "吴烈",
      "target": "中国人民解放军北京卫戍区",
      "type": "MEMBER_OF",
      "properties": {
        "start_date": "1959-01",
        "end_date": "1962-04",
        "position": {
          "zh-cn": "司令员",
          "en": "Commander"
        }
      }
    },
    {
      "source": "朱军 (1971年)",
      "target": "中国人民解放军北京卫戍区",
      "type": "MEMBER_OF",
      "properties": {
        "start_date": "2024-06",
        "position": {
          "zh-cn": "政治委员",
          "en": "Political Commissar"
        }
      }
    },
    {
      "source": "张凡迪",
      "target": "中国人民解放军北京卫戍区",
      "type": "MEMBER_OF",
      "properties": {
        "start_date": "2019-12",
        "end_date": "2023-10",
        "position": {
          "zh-cn": "政治委员",
          "en": "Political Commissar"
        }
      }
    },
    {
      "source": "姜勇 (中将)",
      "target": "中国人民解放军北京卫戍区",
      "type": "MEMBER_OF",
      "properties": {
        "start_date": "2014-12",
        "end_date": "2019-12",
        "position": {
          "zh-cn": "政治委员",
          "en": "Political Commissar"
        }
      }
    },
    {
      "source": "高东璐",
      "target": "中国人民解放军北京卫戍区",
      "type": "MEMBER_OF",
      "properties": {
        "start_date": "2009-12",
        "end_date": "2014-12",
        "position": {
          "zh-cn": "政治委员",
          "en": "Political Commissar"
        }
      }
    },
    {
      "source": "刘福连",
      "target": "中国人民解放军北京卫戍区",
      "type": "MEMBER_OF",
      "properties": {
        "start_date": "2006-12",
        "end_date": "2009-12",
        "position": {
          "zh-cn": "政治委员",
          "en": "Political Commissar"
        }
      }
    },
    {
      "source": "董吉顺",
      "target": "中国人民解放军北京卫戍区",
      "type": "MEMBER_OF",
      "properties": {
        "start_date": "2005-07",
        "end_date": "2006-12",
        "position": {
          "zh-cn": "政治委员",
          "en": "Political Commissar"
        }
      }
    },
    {
      "source": "孙本胜",
      "target": "中国人民解放军北京卫戍区",
      "type": "MEMBER_OF",
      "properties": {
        "start_date": "2002-01",
        "end_date": "2005-07",
        "position": {
          "zh-cn": "政治委员",
          "en": "Political Commissar"
        }
      }
    },
    {
      "source": "李文华 (中将)",
      "target": "中国人民解放军北京卫戍区",
      "type": "MEMBER_OF",
      "properties": {
        "start_date": "1995-12",
        "end_date": "2002-01",
        "position": {
          "zh-cn": "政治委员",
          "en": "Political Commissar"
        }
      }
    },
    {
      "source": "杨惠川",
      "target": "中国人民解放军北京卫戍区",
      "type": "MEMBER_OF",
      "properties": {
        "start_date": "1994-12",
        "end_date": "1995-12",
        "position": {
          "zh-cn": "政治委员",
          "en": "Political Commissar"
        }
      }
    },
    {
      "source": "张宝康",
      "target": "中国人民解放军北京卫戍区",
      "type": "MEMBER_OF",
      "properties": {
        "start_date": "1990-06",
        "end_date": "1994-12",
        "position": {
          "zh-cn": "政治委员",
          "en": "Political Commissar"
        }
      }
    },
    {
      "source": "段君毅",
      "target": "中国人民解放军北京卫戍区",
      "type": "MEMBER_OF",
      "properties": {
        "start_date": "1981-07",
        "end_date": "1984-08",
        "position": {
          "zh-cn": "第一政治委员 (兼)",
          "en": "First Political Commissar (concurrently)"
        }
      }
    },
    {
      "source": "林乎加",
      "target": "中国人民解放军北京卫戍区",
      "type": "MEMBER_OF",
      "properties": {
        "start_date": "1980-12",
        "end_date": "1981-06",
        "position": {
          "zh-cn": "第一政治委员 (兼)",
          "en": "First Political Commissar (concurrently)"
        }
      }
    },
    {
      "source": "李进民",
      "target": "中国人民解放军北京卫戍区",
      "type": "MEMBER_OF",
      "properties": {
        "start_date": "1976-10",
        "end_date": "1990-06",
        "position": {
          "zh-cn": "政治委员",
          "en": "Political Commissar"
        }
      }
    },
    {
      "source": "吴德",
      "target": "中国人民解放军北京卫戍区",
      "type": "MEMBER_OF",
      "properties": {
        "start_date": [
          "1966-07",
          "1968-07",
          "1972-07"
        ],
        "end_date": [
          "1968-07",
          "1972-07",
          "1979-02"
        ],
        "position": {
          "zh-cn": "政治委员",
          "en": "Political Commissar"
        },
        "description": {
          "zh-cn": "先后兼任第一政治委员、第二政治委员、第一政治委员。",
          "en": "Successively served as First Political Commissar, Second Political Commissar, and First Political Commissar, all concurrently."
        }
      }
    },
    {
      "source": "谢富治",
      "target": "中国人民解放军北京卫戍区",
      "type": "MEMBER_OF",
      "properties": {
        "start_date": "1968-07",
        "end_date": "1972-05",
        "position": {
          "zh-cn": "第一政治委员 (兼)",
          "en": "First Political Commissar (concurrently)"
        }
      }
    },
    {
      "source": "刘福 (少将)",
      "target": "中国人民解放军北京卫戍区",
      "type": "MEMBER_OF",
      "properties": {
        "start_date": "1966-05",
        "end_date": "1976-10",
        "position": {
          "zh-cn": "政治委员",
          "en": "Political Commissar"
        }
      }
    },
    {
      "source": "杨俊生 (1916年)",
      "target": "中国人民解放军北京卫戍区",
      "type": "MEMBER_OF",
      "properties": {
        "start_date": "1966-05",
        "end_date": "1987-10",
        "position": {
          "zh-cn": "政治委员",
          "en": "Political Commissar"
        }
      }
    },
    {
      "source": "黄作珍",
      "target": "中国人民解放军北京卫戍区",
      "type": "MEMBER_OF",
      "properties": {
        "start_date": "1966-05",
        "end_date": "1987-10",
        "position": {
          "zh-cn": "第二政治委员",
          "en": "Second Political Commissar"
        }
      }
    },
    {
      "source": "刘绍文",
      "target": "中国人民解放军北京卫戍区",
      "type": "MEMBER_OF",
      "properties": {
        "start_date": "1963-09",
        "end_date": "1966-05",
        "position": {
          "zh-cn": "第二政治委员 (兼)",
          "en": "Second Political Commissar (concurrently)"
        }
      }
    },
    {
      "source": "刘绍文",
      "target": "中国人民解放军北京卫戍区",
      "type": "MEMBER_OF",
      "properties": {
        "start_date": "1966-05",
        "end_date": "1987-10",
        "position": {
          "zh-cn": "第三政治委员 (兼)",
          "en": "Third Political Commissar (concurrently)"
        }
      }
    },
    {
      "source": "刘仁",
      "target": "中国人民解放军北京卫戍区",
      "type": "MEMBER_OF",
      "properties": {
        "start_date": "1959-01",
        "end_date": "1966-08",
        "position": {
          "zh-cn": "第一政治委员 (兼)",
          "en": "First Political Commissar (concurrently)"
        }
      }
    }
  ]
}