{"node": {"id": "Q665554", "type": "Document", "name": {"zh-cn": ["降伏文书", "日本投降书"], "en": ["Japanese Instrument of Surrender"]}, "properties": {"period": "1945-09-02"}}, "relationships": [{"source": "Q665554", "target": "Q702120", "type": "PUSHED", "properties": {"start_date": "1945-09-02"}}, {"source": "Q127417", "target": "Q665554", "type": "INFLUENCED", "properties": {"start_date": "1945-09-02"}}, {"source": "Q665554", "target": "Q362", "type": "BLOCKED", "properties": {"start_date": "1945-09-02"}}, {"source": "Q447077", "target": "Q665554", "type": "PUSHED", "properties": {"start_date": "1945-09-02"}}, {"source": "Q472566", "target": "Q665554", "type": "PUSHED", "properties": {"start_date": "1945-09-02"}}, {"source": "Q127417", "target": "Q665554", "type": "PUSHED", "properties": {"start_date": "1945-09-02"}}]}