{"node": {"id": "Q4475799", "type": "Organization", "name": {"zh-cn": ["兰州大学", "兰大", "兰州中山大学", "兰州医学院", "国立兰州大学", "甘肃公立法政专门学校", "甘肃学院", "甘肃法政学堂", "甘肃省草原生态研究所", "省立甘肃学院"], "en": []}, "properties": {"period": ["1909 - 1913", "1913 - 1928", "1928 - 1931", "1931 - 1946", "1946 - 1949"]}}, "relationships": [{"source": "Q4475799", "target": "Q2502602", "type": "MEMBER_OF", "properties": {"start_date": "2001"}}, {"source": "Q4475799", "target": "Q1970502", "type": "MEMBER_OF", "properties": {"start_date": "1996"}}, {"source": "Q4475799", "target": "Q1042167", "type": "SUBORDINATE_OF"}, {"source": "Q130570174", "target": "Q4475799", "type": "MEMBER_OF", "properties": {"start_date": "2024-09"}}, {"source": "Q104723775", "target": "Q4475799", "type": "MEMBER_OF"}, {"source": "Q8463416", "target": "Q4475799", "type": "MEMBER_OF", "properties": {"start_date": "2017-12", "end_date": "2024-09"}}, {"source": "Q11135599", "target": "Q4475799", "type": "MEMBER_OF", "properties": {"start_date": "1959-01", "end_date": "1966-06"}}, {"source": "Q15921688", "target": "Q4475799", "type": "MEMBER_OF", "properties": {"start_date": "1946", "end_date": "1949"}}, {"source": "Q15942298", "target": "Q4475799", "type": "MEMBER_OF", "properties": {"start_date": "1929", "end_date": "1936"}}, {"source": "BAIDU:蔡大愚", "target": "Q4475799", "type": "MEMBER_OF", "properties": {"start_date": "1913", "end_date": "1917"}}, {"source": "Q10874361", "target": "Q4475799", "type": "INFLUENCED", "properties": {"start_date": "1952"}}, {"source": "BAIDU:西北艺术学院", "target": "Q4475799", "type": "INFLUENCED", "properties": {"start_date": "1953"}}, {"source": "Q4475799", "target": "Q4475799", "type": "FOUNDED", "properties": {"start_date": "1954"}}, {"source": "Q4475799", "target": "Q4475799", "type": "MEMBER_OF", "properties": {"start_date": "2004-11-18"}}, {"source": "Q254204", "target": "Q4475799", "type": "INFLUENCED", "properties": {"start_date": "1965"}}, {"source": "Q4475799", "target": "Q28408664", "type": "MEMBER_OF", "properties": {"start_date": "2017-09-21"}}, {"source": "Q15029", "target": "Q4475799", "type": "PUSHED", "properties": {"start_date": "2009"}}, {"source": "Q455700", "target": "Q4475799", "type": "PUSHED", "properties": {"start_date": "2009"}}, {"source": "Q183679", "target": "Q4475799", "type": "MEMBER_OF"}, {"source": "Q709067", "target": "Q4475799", "type": "MEMBER_OF"}, {"source": "Q874695", "target": "Q4475799", "type": "ALUMNUS_OF"}, {"source": "Q9301044", "target": "Q4475799", "type": "ALUMNUS_OF"}, {"source": "Q6539206", "target": "Q4475799", "type": "ALUMNUS_OF"}, {"source": "Q5950606", "target": "Q4475799", "type": "ALUMNUS_OF"}, {"source": "Q9353760", "target": "Q4475799", "type": "ALUMNUS_OF"}, {"source": "Q9307088", "target": "Q4475799", "type": "ALUMNUS_OF"}, {"source": "Q704051", "target": "Q4475799", "type": "ALUMNUS_OF"}]}